abcattrs/__init__.py
abcattrs/_version.py
abcattrs/abcattrs.py
abcattrs/py.typed
abcattrs/type_hints.py
abcattrs-0.6.1.dist-info/licenses/LICENSE
abcattrs-0.6.1.dist-info/METADATA
abcattrs-0.6.1.dist-info/WHEEL
abcattrs-0.6.1.dist-info/top_level.txt
abcattrs-0.6.1.dist-info/RECORD
