Metadata-Version: 2.4
Name: abcattrs
Version: 0.6.1
Summary: Abstract class attributes
Author-email: Anton Agestam <git@antonagestam.se>
License: BSD-3-Clause
Project-URL: Source Repository, https://github.com/antonagestam/abcattrs/
Classifier: Intended Audience :: Developers
Classifier: Operating System :: OS Independent
Classifier: Programming Language :: Python
Classifier: Programming Language :: Python :: 3
Classifier: Programming Language :: Python :: 3.10
Classifier: Programming Language :: Python :: 3.11
Classifier: Programming Language :: Python :: 3.12
Classifier: Programming Language :: Python :: 3.13
Classifier: Programming Language :: Python :: 3.14
Classifier: Development Status :: 5 - Production/Stable
Classifier: Typing :: Typed
Requires-Python: >=3.10
License-File: LICENSE
Provides-Extra: test
Requires-Dist: pytest; extra == "test"
Requires-Dist: pytest-mypy-plugins; extra == "test"
Requires-Dist: coverage; extra == "test"
Provides-Extra: type-check
Requires-Dist: mypy; extra == "type-check"
Requires-Dist: pytest; extra == "type-check"
Requires-Dist: types-setuptools; extra == "type-check"
Dynamic: license-file
